omic/__init__.py
omic/__main__.py
omic/client.py
omic/const.py
omic/global_.py
omic/omic.py
omic/parallel.py
omic/util.py
omic/entity/__init__.py
omic/entity/clinical.py
omic/entity/cohort.py
omic/entity/data.py
omic/entity/environment.py
omic/entity/execution.py
omic/entity/graph.py
omic/entity/node.py
omic/entity/parameter.py
omic-0.0.13.data/scripts/omic
omic-0.0.13.dist-info/METADATA
omic-0.0.13.dist-info/WHEEL
omic-0.0.13.dist-info/top_level.txt
omic-0.0.13.dist-info/RECORD
