Metadata-Version: 2.1
Name: omic
Version: 0.0.13
Summary: Official Omic client.
Home-page: https://omic.ai
Author: Luke Weber
Author-email: luke@omic.ai
License: MIT
Platform: UNKNOWN
Classifier: Programming Language :: Python :: 3
Classifier: License :: OSI Approved :: MIT License
Classifier: Operating System :: OS Independent
Requires-Dist: fastjsonschema
Requires-Dist: munch
Requires-Dist: pyhumps
Requires-Dist: requests
Requires-Dist: stackeddag
Requires-Dist: tqdm
Requires-Dist: twine
Requires-Dist: validators
